{
  "keep": [
    {
      "rms_id": "4079",
      "title": "Brown Grey Fur Pillow",
      "file": "PILLOWS/Brown Grey fur.png",
      "score": 3
    },
    {
      "rms_id": "4081",
      "title": "Ivory Black Geo Print Pillow",
      "file": "PILLOWS/Ivory Black Geo.png",
      "score": 3
    },
    {
      "rms_id": "4155",
      "title": "Red Zebra Velvet Lumbar Pillow",
      "file": "PILLOWS/Red Zebra Lumbar.png",
      "score": 2
    },
    {
      "rms_id": "4147",
      "title": "Orange Textile Pillow Dos",
      "file": "PILLOWS/Orange Textile Dos.png",
      "score": 3
    },
    {
      "rms_id": "4085",
      "title": "Gold Velvet Fringe Lumbar Pillow",
      "file": "PILLOWS/Gold Fringe Lumbar.png",
      "score": 2
    },
    {
      "rms_id": "3194",
      "title": "White Raffia Pillow",
      "file": "PILLOWS/White Raffia.png",
      "score": 2
    },
    {
      "rms_id": "3925",
      "title": "Bellow 3'H White Corrugated Partition",
      "file": "LARGE-DECOR/BELLOW 3' Partition 1.png",
      "score": 3
    },
    {
      "rms_id": "4152",
      "title": "Black Leather Lattice Pillow",
      "file": "PILLOWS/Black Leather Lattice.png",
      "score": 3
    },
    {
      "rms_id": "2856",
      "title": "Blue Velvet Fringe Lumbar Pillow",
      "file": "PILLOWS/Blue Velvet.png",
      "score": 2
    },
    {
      "rms_id": "4082",
      "title": "Ivory Boucle Pillow",
      "file": "PILLOWS/Ivory Boucle.png",
      "score": 2
    },
    {
      "rms_id": "4157",
      "title": "Silver Leather Woven Pillow",
      "file": "PILLOWS/Silver Leather Woven.png",
      "score": 3
    },
    {
      "rms_id": "2362",
      "title": "Pendleton Grey Cross Throw",
      "file": "THROWS/PENDLETON Grey Cross.png",
      "score": 3
    },
    {
      "rms_id": "2874",
      "title": "Elgin Pony Bronze Bookend Set",
      "file": "STYLING/ELGIN Bronze.png",
      "score": 2
    },
    {
      "rms_id": "2647",
      "title": "Alpaca Snake Oatmeal/Black Throw",
      "file": "_squarespace/652149ab14_ALPACA_Snake_Oatmeal.png",
      "score": 3
    }
  ],
  "blank": [
    {
      "rms_id": "3035",
      "title": "Blue Light Stripe Pillow",
      "file": "PILLOWS/Blue Green Lumbar.png"
    },
    {
      "rms_id": "3091",
      "title": "Blue Light Velvet Pillow",
      "file": "PILLOWS/Blue Green Lumbar.png"
    },
    {
      "rms_id": "2388",
      "title": "Blue Native X Pillow",
      "file": "PILLOWS/Blue Green Lumbar.png"
    },
    {
      "rms_id": "3195",
      "title": "Blue Ombre Fringe Oversize Pillow",
      "file": "PILLOWS/Blue Green Lumbar.png"
    },
    {
      "rms_id": "3098",
      "title": "Blue Sabra Pillow",
      "file": "PILLOWS/Blue Green Lumbar.png"
    },
    {
      "rms_id": "2782",
      "title": "Blue Denim Leather Buckle Pillow",
      "file": "PILLOWS/Blue Green Lumbar.png"
    },
    {
      "rms_id": "2484",
      "title": "Blue Light Velvet Burnout  Pillow",
      "file": "PILLOWS/Blue Green Lumbar.png"
    },
    {
      "rms_id": "3090",
      "title": "Blue Light Velvet Lumbar Pillow",
      "file": "PILLOWS/Blue Green Lumbar.png"
    },
    {
      "rms_id": "2235",
      "title": "Blue Native Pillow",
      "file": "PILLOWS/Blue Green Lumbar.png"
    },
    {
      "rms_id": "3196",
      "title": "Blue Ombre Fringe Oversize Lumbar Pillow",
      "file": "PILLOWS/Blue Green Lumbar.png"
    },
    {
      "rms_id": "2413",
      "title": "Blue Red Native Pillow",
      "file": "PILLOWS/Blue Green Lumbar.png"
    },
    {
      "rms_id": "3100",
      "title": "Blue Turquoise Sabra Pillow",
      "file": "PILLOWS/Blue Green Lumbar.png"
    },
    {
      "rms_id": "3215",
      "title": "Blue Wild Bird Velvet Pillow",
      "file": "PILLOWS/Blue Green Lumbar.png"
    },
    {
      "rms_id": "2244",
      "title": "Brown Faux Mink Oversize Pillow",
      "file": "PILLOWS/Brown Grey fur.png"
    },
    {
      "rms_id": "2242",
      "title": "Brown Fur Square Oversize Pillow",
      "file": "PILLOWS/Brown Grey fur.png"
    },
    {
      "rms_id": "2326",
      "title": "Brown Leather Patchwork Lumbar Pillow",
      "file": "PILLOWS/Brown Grey fur.png"
    },
    {
      "rms_id": "2291",
      "title": "Brown Maroon Leather Pillow",
      "file": "PILLOWS/Brown Grey fur.png"
    },
    {
      "rms_id": "2238",
      "title": "Brown Yellow Grey Wool Pillow",
      "file": "PILLOWS/Brown Grey fur.png"
    },
    {
      "rms_id": "2241",
      "title": "Brown Fur / Mudcloth Long Oversize Pillow",
      "file": "PILLOWS/Brown Grey fur.png"
    },
    {
      "rms_id": "2243",
      "title": "Brown Hide Lumbar Pillow",
      "file": "PILLOWS/Brown Grey fur.png"
    },
    {
      "rms_id": "2916",
      "title": "Brown Light Plaid Pillow",
      "file": "PILLOWS/Brown Grey fur.png"
    },
    {
      "rms_id": "2915",
      "title": "Brown Plaid Pillow",
      "file": "PILLOWS/Brown Grey fur.png"
    },
    {
      "rms_id": "2245",
      "title": "Brown Strip Oversize Pillow",
      "file": "PILLOWS/Brown Grey fur.png"
    },
    {
      "rms_id": "2240",
      "title": "Brown Velvet Quilted Pillow",
      "file": "PILLOWS/Brown Grey fur.png"
    },
    {
      "rms_id": "2287",
      "title": "Ivory Black Native Wool Pillow",
      "file": "PILLOWS/Ivory Black Geo.png"
    },
    {
      "rms_id": "2284",
      "title": "Ivory Gold Textured Pillow",
      "file": "PILLOWS/Ivory Black Geo.png"
    },
    {
      "rms_id": "2857",
      "title": "Ivory Black Plaid Pillow",
      "file": "PILLOWS/Ivory Black Geo.png"
    },
    {
      "rms_id": "2592",
      "title": "Ivory Boho Knit Pillow",
      "file": "PILLOWS/Ivory Black Geo.png"
    },
    {
      "rms_id": "2288",
      "title": "Ivory Brown Chain Link Lumbar Pillow",
      "file": "PILLOWS/Ivory Black Geo.png"
    },
    {
      "rms_id": "2862",
      "title": "Ivory Brown Line Pillow",
      "file": "PILLOWS/Ivory Black Geo.png"
    },
    {
      "rms_id": "2585",
      "title": "Ivory Diamond Shag Pillow",
      "file": "PILLOWS/Ivory Black Geo.png"
    },
    {
      "rms_id": "3088",
      "title": "Ivory Linen Pillow",
      "file": "PILLOWS/Ivory Black Geo.png"
    },
    {
      "rms_id": "3216",
      "title": "Ivory Wild Bird Silk Pillow",
      "file": "PILLOWS/Ivory Black Geo.png"
    },
    {
      "rms_id": "2895",
      "title": "Green Forest Tassel Pillow",
      "file": "PILLOWS/Green Block Print.png"
    },
    {
      "rms_id": "2296",
      "title": "Green Olive Velvet Pillow",
      "file": "PILLOWS/Green Block Print.png"
    },
    {
      "rms_id": "3102",
      "title": "Green Antique Textile Pillow",
      "file": "PILLOWS/Green Block Print.png"
    },
    {
      "rms_id": "2261",
      "title": "Green Dark Velvet Pillow",
      "file": "PILLOWS/Green Block Print.png"
    },
    {
      "rms_id": "2435",
      "title": "Green Olive Faux Silk Pillow",
      "file": "PILLOWS/Green Block Print.png"
    },
    {
      "rms_id": "2297",
      "title": "Green Olive Velvet Lumbar Pillow",
      "file": "PILLOWS/Green Block Print.png"
    },
    {
      "rms_id": "3099",
      "title": "Green Sabra Pillow",
      "file": "PILLOWS/Green Block Print.png"
    },
    {
      "rms_id": "3214",
      "title": "Green Wild Bird Velvet Pillow",
      "file": "PILLOWS/Green Block Print.png"
    },
    {
      "rms_id": "3219",
      "title": "Green Wild Leopard Velvet Pillow",
      "file": "PILLOWS/Green Block Print.png"
    },
    {
      "rms_id": "3812",
      "title": "Red Slightly Darker Velvet Pillow",
      "file": "PILLOWS/Red Zebra Lumbar.png"
    },
    {
      "rms_id": "2917",
      "title": "Red Tan Plaid Oversize Lumbar",
      "file": "PILLOWS/Red Zebra Lumbar.png"
    },
    {
      "rms_id": "2781",
      "title": "Red White Ticking Stripe",
      "file": "PILLOWS/Red Zebra Lumbar.png"
    },
    {
      "rms_id": "2313",
      "title": "Red Velvet Lumbar Pillow",
      "file": "PILLOWS/Red Zebra Lumbar.png"
    },
    {
      "rms_id": "2412",
      "title": "Red Velvet Pillow",
      "file": "PILLOWS/Red Zebra Lumbar.png"
    },
    {
      "rms_id": "2785",
      "title": "Red White Edge Ticking Stripe Pillow",
      "file": "PILLOWS/Red Zebra Lumbar.png"
    },
    {
      "rms_id": "2784",
      "title": "Red White Wide Ticking Stripe Pillow",
      "file": "PILLOWS/Red Zebra Lumbar.png"
    },
    {
      "rms_id": "2910",
      "title": "Orange Ivory Native Pillow",
      "file": "PILLOWS/Orange Textile Dos.png"
    },
    {
      "rms_id": "2855",
      "title": "Orange Copper Velvet Fringe Lumbar Pillow",
      "file": "PILLOWS/Orange Textile Dos.png"
    },
    {
      "rms_id": "2882",
      "title": "Orange Textile Pillow Uno",
      "file": "PILLOWS/Orange Textile Dos.png"
    },
    {
      "rms_id": "2304",
      "title": "Orange Velvet Quilted Pillow",
      "file": "PILLOWS/Orange Textile Dos.png"
    },
    {
      "rms_id": "2257",
      "title": "Gold Fleck Woven Pillow",
      "file": "PILLOWS/Gold Fringe Lumbar.png"
    },
    {
      "rms_id": "2394",
      "title": "Gold Speckled Leather Pillow",
      "file": "PILLOWS/Gold Fringe Lumbar.png"
    },
    {
      "rms_id": "2593",
      "title": "Gold Velvet Dotted Pillow",
      "file": "PILLOWS/Gold Fringe Lumbar.png"
    },
    {
      "rms_id": "2323",
      "title": "White Hide Lumbar Pillow",
      "file": "PILLOWS/White Raffia.png"
    },
    {
      "rms_id": "2603",
      "title": "White Hide Stitched Lumbar Pillow",
      "file": "PILLOWS/White Raffia.png"
    },
    {
      "rms_id": "2325",
      "title": "White Silver Hide Pillow",
      "file": "PILLOWS/White Raffia.png"
    },
    {
      "rms_id": "2419",
      "title": "Pink Black Abstract Lumbar Pillow",
      "file": "PILLOWS/Pink and Yellow.png"
    },
    {
      "rms_id": "3217",
      "title": "Pink Wild Lynx Velvet Pillow",
      "file": "PILLOWS/Pink and Yellow.png"
    },
    {
      "rms_id": "2894",
      "title": "Pink Hot Velvet Pillow",
      "file": "PILLOWS/Pink and Yellow.png"
    },
    {
      "rms_id": "2015",
      "title": "Bellow 8'H White Corrugated Wall",
      "file": "LARGE-DECOR/BELLOW 3' Partition 1.png"
    },
    {
      "rms_id": "3524",
      "title": "Hudson Rock Wall",
      "file": "LARGE-DECOR/HUDSON Render.png"
    },
    {
      "rms_id": "3611",
      "title": "Hudson Rock Wall with Shelves",
      "file": "LARGE-DECOR/HUDSON Render.png"
    },
    {
      "rms_id": "3092",
      "title": "Black Brown Plaid Pillow",
      "file": "PILLOWS/Black Cream Dimensional.png"
    },
    {
      "rms_id": "2393",
      "title": "Black Hide Lumbar Pillow",
      "file": "PILLOWS/Black Cream Dimensional.png"
    },
    {
      "rms_id": "2230",
      "title": "Black Leather Lumbar Pillow",
      "file": "PILLOWS/Black Leather Lattice.png"
    },
    {
      "rms_id": "2427",
      "title": "Blue Velvet Brocade Lumbar Pillow",
      "file": "PILLOWS/Blue Velvet.png"
    },
    {
      "rms_id": "2847",
      "title": "Ivory Seamed Boucle Pillow",
      "file": "PILLOWS/Ivory Boucle.png"
    },
    {
      "rms_id": "3149",
      "title": "Silver Disco Pillow",
      "file": "PILLOWS/Silver Leather Woven.png"
    },
    {
      "rms_id": "1614",
      "title": "Pendleton Neutral ZigZag Throw",
      "file": "THROWS/PENDLETON Grey Cross.png"
    },
    {
      "rms_id": "2873",
      "title": "Elgin Pony Silver Bookend Set",
      "file": "STYLING/ELGIN Bronze.png"
    },
    {
      "rms_id": "2646",
      "title": "Alpaca Snake Grey/Black Throw",
      "file": "_squarespace/652149ab14_ALPACA_Snake_Oatmeal.png"
    }
  ]
}